Metadata-Version: 2.4
Name: insightface-rk
Version: 0.7.3
Summary: Enhanced face analysis package with frontal face detection and filtering largest face / small faces
Home-page: https://github.com/minhntt3-rikkei/insightface-rk
Author: Rikkeisoft - MinhNTT3, Rikkeisoft - LinhPD2
Author-email: minhntt3@rikkeisoft.com, linhpd2@rikkeisoft.com
License: MIT
Keywords: face detection recognition insightface computer-vision machine-learning
Classifier: Development Status :: 4 - Beta
Classifier: Intended Audience :: Developers
Classifier: License :: OSI Approved :: MIT License
Classifier: Programming Language :: Python :: 3
Classifier: Programming Language :: Python :: 3.8
Classifier: Programming Language :: Python :: 3.9
Classifier: Programming Language :: Python :: 3.10
Classifier: Programming Language :: Python :: 3.11
Classifier: Programming Language :: Python :: 3.12
Classifier: Programming Language :: Python :: 3.13
Classifier: Topic :: Scientific/Engineering :: Image Recognition
Classifier: Topic :: Software Development :: Libraries :: Python Modules
Requires-Python: >=3.8
License-File: LICENSE
Requires-Dist: numpy
Requires-Dist: onnx
Requires-Dist: onnxruntime
Requires-Dist: tqdm
Requires-Dist: requests
Requires-Dist: matplotlib
Requires-Dist: opencv-python
Requires-Dist: scikit-image
Requires-Dist: albumentations
Dynamic: author
Dynamic: author-email
Dynamic: classifier
Dynamic: description
Dynamic: description-content-type
Dynamic: home-page
Dynamic: keywords
Dynamic: license
Dynamic: license-file
Dynamic: requires-dist
Dynamic: requires-python
Dynamic: summary
